[{"anonymous": [], "word_count": "52", "_id": "542151bb7988104c4a50251a", "persons": ["Robinson, Jeff"], "female": [], "pub_date": "2010-12-14T00:00:00Z", "subject": ["College Athletics", "Basketball"], "organizations": ["Seton Hall University"], "news_desk": "Sports", "lead_paragraph": "The freshman forward Fuquan Edwin scored 17 points and grabbed 9 rebounds, both career highs, to pace Seton Hall to an easy 78-51 victory over Longwood.", "snippet": "The freshman forward Fuquan Edwin scored 17 points and grabbed 9 rebounds, both career highs, to pace Seton Hall to an easy 78-51 victory over Longwood.", "subsection_name": "College Basketball", "male": ["Jeff"]}]