[{"anonymous": [], "word_count": "287", "_id": "548d7668798810543aba5924", "persons": ["Auriemma, Geno"], "female": [], "pub_date": "2007-01-07T00:00:00Z", "subject": ["Basketball", "College Athletics"], "organizations": ["University of Connecticut"], "news_desk": "Sports", "lead_paragraph": "Geno Auriemma, in his 22nd season as coach of the University of Connecticut women\u2019s basketball team, recorded his 600th victory last week. ", "snippet": "Geno Auriemma, in his 22nd season as coach of the University of Connecticut women\u2019s basketball team, recorded his 600th victory last week.", "subsection_name": "College Basketball", "male": ["Geno"]}]