[{"anonymous": [], "word_count": "1089", "_id": "5415efb679881072eb9ef2fc", "persons": ["Hackenberg, Christian", "O'Brien, Bill", "Franklin, James E (1972- )"], "female": [], "pub_date": "2014-09-15T00:00:00Z", "subject": ["Football (College)"], "organizations": ["Pennsylvania State University", "Rutgers, The State University of New Jersey"], "news_desk": "Sports", "lead_paragraph": "Hackenberg, a 19-year-old sophomore, behaves like the adult of the revitalized Nittany Lions, standing for something beyond the obvious tangible rewards of the game.", "snippet": "Hackenberg, a 19-year-old sophomore, behaves like the adult of the revitalized Nittany Lions, standing for something beyond the obvious tangible rewards of the game.", "subsection_name": "College Football", "male": ["Christian", "Bill", "James"]}]