[{"anonymous": [], "word_count": "956", "_id": "55b0477d7988101f175e8947", "persons": ["Miller, Andrew (1985- )", "Showalter, Buck"], "female": [], "pub_date": "2015-07-23T00:00:00Z", "subject": ["Baseball", "Trades (Sports)"], "organizations": ["Baltimore Orioles", "New York Yankees"], "news_desk": "Sports", "lead_paragraph": "Miller, who fortified Baltimore\u2019s bullpen during the latter part of last season and has given the Yankees a lift this year, illustrates how a move at the trading deadline can change a team\u2019s postseason trajectory.", "snippet": "Miller, who fortified Baltimore\u2019s bullpen during the latter part of last season and has given the Yankees a lift this year, illustrates how a move at the trading deadline can change a team\u2019s postseason trajectory.", "subsection_name": "Baseball", "male": ["Andrew", "Buck"]}]