[{"anonymous": [], "word_count": "23", "_id": "5590ff5d79881030910bfa40", "persons": ["Bud", "Lou"], "female": [], "pub_date": "2015-06-29T04:18:09Z", "subject": null, "organizations": null, "news_desk": "Movies", "lead_paragraph": "Bud and Lou enlist in the army in order to escape being hauled off to jail, and soon find themselves in boot camp.", "snippet": "Bud and Lou enlist in the army in order to escape being hauled off to jail, and soon find themselves in boot camp.", "subsection_name": null, "male": ["Bud", "Lou"]}]