[{"anonymous": [], "word_count": "373", "_id": "531fe37579881012a4bf0042", "persons": ["Holden, Stuart"], "female": [], "pub_date": "2014-03-12T00:00:00Z", "subject": ["Soccer", "World Cup 2014 (Soccer)"], "organizations": ["United States Men's National Soccer Team"], "news_desk": "Sports", "lead_paragraph": "The oft-injured midfielder Stuart Holden will miss six to nine months after his latest knee operation, but his news this week wasn\u2019t all bad.", "snippet": "The oft-injured midfielder Stuart Holden will miss six to nine months after his latest knee operation, but his news this week wasn\u2019t all bad.", "subsection_name": "Soccer", "male": ["Stuart"]}]