[{"anonymous": ["Lytle"], "word_count": "238", "_id": "5420dd747988104c4a501aea", "persons": ["Lytle"], "female": [], "pub_date": "2010-11-22T00:00:00Z", "subject": ["Football", "Deaths (Obituaries)"], "organizations": ["Denver Broncos"], "news_desk": "Sports", "lead_paragraph": "After a star turn as a running back at Michigan, Lytle scored a touchdown in the 1978 Super Bowl as a Denver Broncos rookie.", "snippet": "After a star turn as a running back at Michigan, Lytle scored a touchdown in the 1978 Super Bowl as a Denver Broncos rookie.", "subsection_name": "Pro Football", "male": []}]