[{"anonymous": [], "word_count": "120", "_id": "55d94c25798810795b5fb92b", "persons": ["Peter Sowrey"], "female": [], "pub_date": "2015-08-23T00:00:00Z", "subject": ["Olympic Games (2016)", "Sailboats and Sailing", "Water Pollution"], "organizations": ["International Olympic Committee"], "news_desk": "Sports", "lead_paragraph": "Peter Sowrey, the chief executive of sailing\u2019s governing body, threatened to move all sailing events at next year\u2019s Olympics in Rio de Janeiro out of the polluted Guanabara Bay unless the water is cleaner.", "snippet": "Peter Sowrey, the chief executive of sailing\u2019s governing body, threatened to move all sailing events at next year\u2019s Olympics in Rio de Janeiro out of the polluted Guanabara Bay unless the water is cleaner.", "subsection_name": "Olympics", "male": ["Peter"]}]