[{"anonymous": [], "word_count": "1081", "_id": "5443817d7988103ffb145854", "persons": ["Jackson, Jess"], "female": [], "pub_date": "2010-03-04T00:00:00Z", "subject": ["Zenyatta (Race Horse)", "Rachel Alexandra (Race Horse)", "Horse Racing"], "organizations": null, "news_desk": "Sports", "lead_paragraph": "Will Rachel Alexandra, the Horse of the Year, and Zenyatta, the Breeders\u2019 Cup Classic winner, show up for the Apple Blossom Invitational on April 9?", "snippet": "Will Rachel Alexandra, the Horse of the Year, and Zenyatta, the Breeders\u2019 Cup Classic winner, show up for the Apple Blossom Invitational on April 9?", "subsection_name": null, "male": ["Jess"]}]