[{"anonymous": [], "word_count": "51", "_id": "54442ee779881076287712e6", "persons": ["Ron Turner", "Ron Prince"], "female": [], "pub_date": "2010-03-21T00:00:00Z", "subject": ["Coaches and Managers", "Football"], "organizations": ["Indianapolis Colts"], "news_desk": "Sports", "lead_paragraph": "The Colts hired the former Bears offensive coordinator Ron Turner as wide receivers coach, and the former Virginia special teams coordinator Ron Prince as assistant offensive line coach.", "snippet": "The Colts hired the former Bears offensive coordinator Ron Turner as wide receivers coach, and the former Virginia special teams coordinator Ron Prince as assistant offensive line coach.", "subsection_name": "Pro Football", "male": ["Ron", "Ron"]}]