[{"anonymous": [], "word_count": "589", "_id": "5173486cfdc59276ee001c8c", "persons": ["Chandler, Tyson", "Martin, Kenyon"], "female": [], "pub_date": "2013-04-21T00:00:00Z", "subject": ["Basketball", "Sports Injuries"], "organizations": ["New York Knicks", "Boston Celtics"], "news_desk": "Sports", "lead_paragraph": "Kenyon Martin, in his return from a sprained ankle, had a strong second half as Tyson Chandler struggled to find his rhythm in his return from a neck injury.", "snippet": "Kenyon Martin, in his return from a sprained ankle, had a strong second half as Tyson Chandler struggled to find his rhythm in his return from a neck injury.", "subsection_name": "Pro Basketball", "male": ["Tyson", "Kenyon"]}]