[{"anonymous": [], "word_count": "989", "_id": "515a944dfdc59278db00581f", "persons": ["Kelly, Brian"], "female": [], "pub_date": "2011-08-18T00:00:00Z", "subject": ["Football", "College Athletics", "Football (College)", "Coaches and Managers"], "organizations": ["University of Notre Dame"], "news_desk": "Sports", "lead_paragraph": "Brian Kelly\u2019s successes in 2010 \u2014 the program\u2019s first win over Southern California since 2001 and second bowl win since 1994 \u2014 were overshadowed by off-field tragedies.", "snippet": "Brian Kelly\u2019s successes in 2010 \u2014 the program\u2019s first win over Southern California since 2001 and second bowl win since 1994 \u2014 were overshadowed by off-field tragedies.", "subsection_name": "College Football", "male": ["Brian"]}]