[{"anonymous": ["Dellin"], "word_count": "953", "_id": "53dda92779881018c3d0923c", "persons": ["Betances, Dellin", "Robertson, David (1985- )", "Rivera, Mariano", "Girardi, Joe"], "female": [], "pub_date": "2014-08-03T00:00:00Z", "subject": ["Baseball"], "organizations": ["New York Yankees"], "news_desk": "Sports", "lead_paragraph": "In the first season since Mariano Rivera's retirement, the Yankees have been able to rely on Dellin Betances and David Robertson.", "snippet": "In the first season since Mariano Rivera's retirement, the Yankees have been able to rely on Dellin Betances and David Robertson.", "subsection_name": "Baseball", "male": ["David", "Mariano", "Joe"]}]