[{"anonymous": ["Jirik"], "word_count": "367", "_id": "515b980afdc59278db00d10e", "persons": ["Jirik"], "female": [], "pub_date": "2011-07-13T00:00:00Z", "subject": ["Hockey, Ice", "Deaths (Obituaries)", "Politics and Government"], "organizations": ["National Hockey League"], "news_desk": "Sports", "lead_paragraph": "Jirik was a Czech hockey star who played a role in his national team\u2019s emotional victory over the Soviets in 1969.", "snippet": "Jirik was a Czech hockey star who played a role in his national team\u2019s emotional victory over the Soviets in 1969.", "subsection_name": "Hockey", "male": []}]