[{"anonymous": [], "word_count": "401", "_id": "529eb15879881035109203e8", "persons": ["Kyle Singler", "Andre Drummond"], "female": ["Kyle"], "pub_date": "2013-12-04T00:00:00Z", "subject": ["Basketball"], "organizations": ["Miami Heat", "Detroit Pistons"], "news_desk": "Sports", "lead_paragraph": "Kyle Singler scored 18 points to lead seven Detroit players in double figures, Andre Drummond had 18 rebounds as the Pistons ended Miami&#8217;s winning streak at 10 games.", "snippet": "Kyle Singler scored 18 points to lead seven Detroit players in double figures, Andre Drummond had 18 rebounds as the Pistons ended Miami&#8217;s winning streak at 10 games.", "subsection_name": "Pro Basketball", "male": ["Andre"]}]