[{"anonymous": [], "word_count": "631", "_id": "52bfa57a798810447146aea9", "persons": ["Hilary Knight"], "female": ["Hilary"], "pub_date": "2013-12-29T00:00:00Z", "subject": ["Hockey, Ice", "Olympic Games (2014)"], "organizations": null, "news_desk": "Sports", "lead_paragraph": "Hilary Knight scored in a shootout to deliver a 3-2 victory for the Americans, their third consecutive win over the Canadians this month in pre-Olympic exhibition games.", "snippet": "Hilary Knight scored in a shootout to deliver a 3-2 victory for the Americans, their third consecutive win over the Canadians this month in pre-Olympic exhibition games.", "subsection_name": "Olympics", "male": []}]