[{"anonymous": ["LeBron", "Brook"], "word_count": "888", "_id": "510a336f00315214fbb88229", "persons": ["James, LeBron", "Lopez, Brook", "Chalmers, Mario"], "female": [], "pub_date": "2013-01-31T00:00:00Z", "subject": ["Basketball"], "organizations": ["Brooklyn Nets", "Miami Heat"], "news_desk": "Sports", "lead_paragraph": "LeBron James and Dwyane Wade put together a highlight reel of dunks while leading the Heat to a rout at Barclays Center, ending the Nets\u2019 eight-game home winning streak.", "snippet": "LeBron James and Dwyane Wade put together a highlight reel of dunks while leading the Heat to a rout at Barclays Center, ending the Nets\u2019 eight-game home winning streak.", "subsection_name": "Pro Basketball", "male": ["Mario"]}]