[{"anonymous": [], "word_count": "1426", "_id": "50f5b3b100315214fbb8517b", "persons": ["Federer, Roger"], "female": [], "pub_date": "2013-01-16T20:55:00Z", "subject": ["Australian Open (Tennis)", "United States Open (Tennis)", "Tennis"], "organizations": ["United States Tennis Assn"], "news_desk": "Sports", "lead_paragraph": "The Australian Open is in the midst of a growth spurt, and its officials have been openly supportive of men\u2019s players\u2019 demands for a bigger percentage of Grand Slam revenue.", "snippet": "The Australian Open is in the midst of a growth spurt, and its officials have been openly supportive of men\u2019s players\u2019 demands for a bigger percentage of Grand Slam revenue.", "subsection_name": "Tennis", "male": ["Roger"]}]