[{"anonymous": [], "word_count": "617", "_id": "50be625200315214fbb7d516", "persons": ["Wilson, Russell"], "female": [], "pub_date": "2012-12-03T00:00:00Z", "subject": ["Football"], "organizations": ["Seattle Seahawks", "Chicago Bears"], "news_desk": "Sports", "lead_paragraph": "Russell Wilson, overshadowed by the fellow rookie quarterbacks Andrew Luck and Robert Griffin III, led Seattle to an overtime win Sunday in Chicago.", "snippet": "Russell Wilson, overshadowed by the fellow rookie quarterbacks Andrew Luck and Robert Griffin III, led Seattle to an overtime win Sunday in Chicago.", "subsection_name": "Pro Football", "male": ["Russell"]}]