[{"anonymous": [], "word_count": "1971", "_id": "50be626300315214fbb7d66e", "persons": null, "female": [], "pub_date": "2012-12-05T00:00:00Z", "subject": ["Football"], "organizations": ["Elite Football League of India"], "news_desk": "Sports", "lead_paragraph": "The Elite Football League of India, a curious venture aimed at introducing the American sport to South Asia, has a low level of play but a large potential audience.", "snippet": "The Elite Football League of India, a curious venture aimed at introducing the American sport to South Asia, has a low level of play but a large potential audience.", "subsection_name": "Pro Football", "male": []}]