[{"anonymous": [], "word_count": "1075", "_id": "561c2274798810413432c897", "persons": ["Utley, Chase", "Harvey, Matt"], "female": [], "pub_date": "2015-10-13T00:00:00Z", "subject": ["Baseball"], "organizations": ["New York Mets", "Los Angeles Dodgers"], "news_desk": "Sports", "lead_paragraph": "How fans and the Mets react to Chase Utley\u2019s aggressive slide, which broke the leg of shortstop Ruben Tejada, will not be known until Game 3 on Monday night.", "snippet": "How fans and the Mets react to Chase Utley\u2019s aggressive slide, which broke the leg of shortstop Ruben Tejada, will not be known until Game 3 on Monday night.", "subsection_name": "Baseball", "male": ["Chase", "Matt"]}]