[{"anonymous": [], "word_count": "789", "_id": "5397bcc97988104e442a7c5e", "persons": ["Griner, Brittney"], "female": ["Brittney"], "pub_date": "2014-06-11T00:00:00Z", "subject": ["Homosexuality and Bisexuality", "Basketball", "Advertising and Marketing", "Transgender and Transsexual"], "organizations": ["Women's National Basketball Assn"], "news_desk": "Sports", "lead_paragraph": "Now that the coast is clear, the W.N.B.A., which has been around for nearly two decades, has decided to publicly embrace its gay fans. The gesture deserves two slow claps, considering how long it took.", "snippet": "Now that the coast is clear, the W.N.B.A., which has been around for nearly two decades, has decided to publicly embrace its gay fans. The gesture deserves two slow claps, considering how long it took.", "subsection_name": null, "male": []}]