[{"anonymous": [], "word_count": "50", "_id": "53a3ba197988106a6836c4e2", "persons": ["Kelly, Jim (1960- )"], "female": [], "pub_date": "2014-06-20T00:00:00Z", "subject": ["Football"], "organizations": ["Buffalo Bills"], "news_desk": "Sports", "lead_paragraph": "The Hall of Fame quarterback Jim Kelly took a break from his recovery from cancer treatments to make a surprise appearance at the Buffalo Bills\u2019 practice.", "snippet": "The Hall of Fame quarterback Jim Kelly took a break from his recovery from cancer treatments to make a surprise appearance at the Buffalo Bills\u2019 practice.", "subsection_name": "Pro Football", "male": ["Jim"]}]