[{"anonymous": [], "word_count": "939", "_id": "515a22f8fdc59278db0017f0", "persons": ["Ryan, Rex", "Sanchez, Mark", "Sparano, Tony"], "female": [], "pub_date": "2012-08-27T00:00:00Z", "subject": ["Football"], "organizations": ["New York Jets", "Carolina Panthers"], "news_desk": "Sports", "lead_paragraph": "The Jets\u2019 first-team defense forced three fumbles and largely contained the Panthers\u2019 athletic quarterback Cam Newton, but the offense was held out of the end zone for a third time.", "snippet": "The Jets\u2019 first-team defense forced three fumbles and largely contained the Panthers\u2019 athletic quarterback Cam Newton, but the offense was held out of the end zone for a third time.", "subsection_name": "Pro Football", "male": ["Rex", "Mark", "Tony"]}]