[{"anonymous": ["Bronte"], "word_count": "198", "_id": "515a2b6cfdc59278db001cc8", "persons": ["Schmitt, Allison", "Franklin, Missy", "Barratt, Bronte", "Muffat, Camille (1989-2015)"], "female": ["Allison", "Missy", "Camille"], "pub_date": "2012-08-01T00:00:00Z", "subject": ["Swimming", "Olympic Games (2012)", "Records and Achievements"], "organizations": null, "news_desk": "Sports", "lead_paragraph": "Allison Schmitt defeated a deep field that included the previous record-holder, the defending gold medalist, the fastest qualifier and her teammate Missy Franklin.", "snippet": "Allison Schmitt defeated a deep field that included the previous record-holder, the defending gold medalist, the fastest qualifier and her teammate Missy Franklin.", "subsection_name": "Olympics", "male": []}]