[{"anonymous": [], "word_count": "752", "_id": "515a255ffdc59278db001958", "persons": ["Nathan, Joe"], "female": [], "pub_date": "2012-08-19T00:00:00Z", "subject": ["Baseball", "Records and Achievements"], "organizations": ["Texas Rangers", "Toronto Blue Jays"], "news_desk": "Sports", "lead_paragraph": "Joe Nathan converted his 22nd straight save opportunity in a 2-1 victory at Toronto. The save broke a team record set by Francisco Cordero in 2004.", "snippet": "Joe Nathan converted his 22nd straight save opportunity in a 2-1 victory at Toronto. The save broke a team record set by Francisco Cordero in 2004.", "subsection_name": "Baseball", "male": ["Joe"]}]