[{"anonymous": [], "word_count": "360", "_id": "515a666ffdc59278db003eda", "persons": ["Lidstrom, Nicklas"], "female": [], "pub_date": "2012-02-13T00:00:00Z", "subject": ["Hockey, Ice"], "organizations": ["Detroit Red Wings", "Philadelphia Flyers", "Florida Panthers", "New York Islanders"], "news_desk": "Sports", "lead_paragraph": "Detroit equaled an N.H.L. record with their 20th straight home win, and Nicklas Lidstrom played in his 1,550th game, the most by a player who spent his entire career with one team.", "snippet": "Detroit equaled an N.H.L. record with their 20th straight home win, and Nicklas Lidstrom played in his 1,550th game, the most by a player who spent his entire career with one team.", "subsection_name": "Hockey", "male": ["Nicklas"]}]