[{"anonymous": [], "word_count": "633", "_id": "548761bb798810726e2d305d", "persons": ["Gail Goestenkors"], "female": ["Gail"], "pub_date": "2007-11-11T00:00:00Z", "subject": ["Basketball", "College Athletics"], "organizations": ["University of Texas at Austin"], "news_desk": "Sports", "lead_paragraph": "Gail Goestenkors had just settled in from the whirlwind of becoming the new head coach at Texas when she got her first piece of bad news.", "snippet": "Gail Goestenkors had just settled in from the whirlwind of becoming the new head coach at Texas when she got her first piece of bad news.", "subsection_name": "College Basketball", "male": []}]