[{"anonymous": [], "word_count": "839", "_id": "5457d3cb798810533a8dd787", "persons": ["Teixeira, Mark", "Rodriguez, Alex", "Damon, Johnny", "Girardi, Joe"], "female": [], "pub_date": "2009-10-30T00:00:00Z", "subject": ["Baseball", "Playoff Games"], "organizations": ["New York Yankees"], "news_desk": "Sports", "lead_paragraph": "Because this has been a postseason in which Mark Teixeira has not always had positive things to discuss, he has devised an escape hatch.", "snippet": "Because this has been a postseason in which Mark Teixeira has not always had positive things to discuss, he has devised an escape hatch.", "subsection_name": "Baseball", "male": ["Mark", "Alex", "Johnny", "Joe"]}]