[{"anonymous": [], "word_count": "547", "_id": "544498bf7988107628771bee", "persons": null, "female": [], "pub_date": "2010-04-01T00:00:00Z", "subject": ["Hockey, Ice"], "organizations": ["New York Rangers"], "news_desk": "Sports", "lead_paragraph": "The schedule for the 10th-place Rangers appears to be substantially easier than that of two of the teams directly above them.", "snippet": "The schedule for the 10th-place Rangers appears to be substantially easier than that of two of the teams directly above them.", "subsection_name": "Hockey", "male": []}]