[{"anonymous": [], "word_count": "569", "_id": "515a9c9ffdc59278db005ce9", "persons": ["McDowell, Roger", "Lowe, Derek"], "female": [], "pub_date": "2011-04-30T00:00:00Z", "subject": ["Baseball", "Coaches and Managers", "Drunken and Reckless Driving"], "organizations": ["Atlanta Braves", "Major League Baseball"], "news_desk": "Sports", "lead_paragraph": "The pitching coach Roger McDowell, accused of antigay slurs and a threat, was put on leave pending an investigation, and pitcher Derek Lowe faces a D.U.I. charge.", "snippet": "The pitching coach Roger McDowell, accused of antigay slurs and a threat, was put on leave pending an investigation, and pitcher Derek Lowe faces a D.U.I. charge.", "subsection_name": "Baseball", "male": ["Roger", "Derek"]}]