[{"anonymous": ["Usain"], "word_count": "89", "_id": "5446e21179881004ee627c34", "persons": ["Bolt, Usain", "Johnson, Michael"], "female": [], "pub_date": "2010-05-28T00:00:00Z", "subject": ["Track and Field"], "organizations": null, "news_desk": "Sports", "lead_paragraph": "Usain Bolt won a rarely contested 300-meter race in 30.97 seconds in the rain at the Golden Spike meet in Ostrava, Czech Republic. ", "snippet": "Usain Bolt won a rarely contested 300-meter race in 30.97 seconds in the rain at the Golden Spike meet in Ostrava, Czech Republic.", "subsection_name": null, "male": ["Michael"]}]