[{"anonymous": [], "word_count": "786", "_id": "54461716798810347c1a9231", "persons": ["Michael Leighton", "Brian Boucher"], "female": [], "pub_date": "2010-05-12T00:00:00Z", "subject": ["Hockey, Ice"], "organizations": ["Philadelphia Flyers", "Boston Bruins"], "news_desk": "Sports", "lead_paragraph": "Michael Leighton, back in goal after Brian Boucher was injured, will try to keep Philadelphia rebounding from a 3-0 deficit against the Boston Bruins.", "snippet": "Michael Leighton, back in goal after Brian Boucher was injured, will try to keep Philadelphia rebounding from a 3-0 deficit against the Boston Bruins.", "subsection_name": "Hockey", "male": ["Michael", "Brian"]}]