[{"anonymous": [], "word_count": "800", "_id": "515a429ffdc59278db002a1f", "persons": ["John Tortorella"], "female": [], "pub_date": "2012-05-23T00:00:00Z", "subject": ["Stanley Cup", "Hockey, Ice", "Playoff Games"], "organizations": ["New York Rangers", "New Jersey Devils"], "news_desk": "Sports", "lead_paragraph": "The Rangers will need more than divine intervention and the resilience that Coach John Tortorella said \u201cdefines our team\u201d if they are to take a 3-2 lead in the Eastern Conference finals.", "snippet": "The Rangers will need more than divine intervention and the resilience that Coach John Tortorella said \u201cdefines our team\u201d if they are to take a 3-2 lead in the Eastern Conference finals.", "subsection_name": "Hockey", "male": ["John"]}]