[{"anonymous": [], "word_count": "988", "_id": "51e171fd7988102a01491be8", "persons": null, "female": [], "pub_date": "2013-07-14T00:00:00Z", "subject": ["Baseball", "All Star Games"], "organizations": ["Citi Field (NYC)", "New York Mets"], "news_desk": "Sports", "lead_paragraph": "Before the end of the 2012 season, the All-Star Game host Mets used tickets to the game and festivities as a vehicle to sell season tickets to their fans.", "snippet": "Before the end of the 2012 season, the All-Star Game host Mets used tickets to the game and festivities as a vehicle to sell season tickets to their fans.", "subsection_name": "Baseball", "male": []}]