[{"anonymous": [], "word_count": "386", "_id": "52953fa079881027a28fab60", "persons": ["Alderson, Sandy", "Wright, David", "Young, Chris (1979- )"], "female": ["Sandy"], "pub_date": "2013-11-27T00:00:00Z", "subject": ["Baseball"], "organizations": ["New York Mets"], "news_desk": "Sports", "lead_paragraph": "David Wright says he is \u201cpretty impatient\u201d with the Mets\u2019 off-season plans, one piece of which fell into place with the announcement that outfielder Chris Young had signed a $7.25 million deal.", "snippet": "David Wright says he is \u201cpretty impatient\u201d with the Mets\u2019 off-season plans, one piece of which fell into place with the announcement that outfielder Chris Young had signed a $7.25 million deal.", "subsection_name": "Baseball", "male": ["David", "Chris"]}]