[{"anonymous": ["Callaway"], "word_count": "752", "_id": "54718fca7988107046477644", "persons": ["Callaway"], "female": [], "pub_date": "2009-01-11T00:00:00Z", "subject": ["Golf"], "organizations": ["Titleist"], "news_desk": "Sports", "lead_paragraph": "Titleist is involved in a dispute with Callaway over patents applied to the Pro V1 ball. Two courts have ruled in favor of Callaway, and Titleist is appealing.", "snippet": "Titleist is involved in a dispute with Callaway over patents applied to the Pro V1 ball. Two courts have ruled in favor of Callaway, and Titleist is appealing.", "subsection_name": "Golf", "male": []}]