[{"anonymous": ["Edberg"], "word_count": "70", "_id": "548193007988103739e18245", "persons": ["Stefan Edberg", "Edberg", "Pete Sampras"], "female": [], "pub_date": "2008-05-20T00:00:00Z", "subject": ["Paralympic Games", "Cocaine and Crack Cocaine"], "organizations": ["Court of Arbitration for Sport"], "news_desk": "Sports", "lead_paragraph": "Stefan Edberg will return to competitive tennis for the first time in 12 years with two matches on the senior tour. Edberg, 42, who won two Wimbledon titles among his six Grand Slam crowns, had declined to play seniors events but changed his mind when Pete Sampras announced he would play two events this year.", "snippet": "Stefan Edberg will return to competitive tennis for the first time in 12 years with two matches on the senior tour. Edberg, 42, who won two Wimbledon titles among his six Grand Slam crowns, had declined to play seniors events but changed his mind...", "subsection_name": "Olympics", "male": ["Stefan", "Pete"]}]