[{"anonymous": [], "word_count": "1084", "_id": "546af3897988106d5f6273e4", "persons": ["Billups, Chauncey"], "female": [], "pub_date": "2009-05-24T00:00:00Z", "subject": ["Basketball"], "organizations": ["Denver Nuggets"], "news_desk": "Sports", "lead_paragraph": "Chauncey Billups is widely credited for lifting an unappealing and underachieving collection of basketball parts into a frenzy-inducing championship contender.", "snippet": "Chauncey Billups is widely credited for lifting an unappealing and underachieving collection of basketball parts into a frenzy-inducing championship contender.", "subsection_name": "Pro Basketball", "male": ["Chauncey"]}]