[{"anonymous": [], "word_count": "42", "_id": "548291577988101355140b2a", "persons": ["Katinka Hosszu"], "female": ["Katinka"], "pub_date": "2014-12-06T00:00:00Z", "subject": ["Swimming"], "organizations": null, "news_desk": "Sports", "lead_paragraph": "Katinka Hosszu of Hungary broke two world records at the short-course world championships in Doha, Qatar, in the women\u2019s 200-meter backstroke and 100 individual medley.", "snippet": "Katinka Hosszu of Hungary broke two world records at the short-course world championships in Doha, Qatar, in the women\u2019s 200-meter backstroke and 100 individual medley.", "subsection_name": null, "male": []}]