[{"anonymous": [], "word_count": "856", "_id": "515a307afdc59278db001fae", "persons": ["Fedrigo, Pierrick"], "female": [], "pub_date": "2012-07-17T20:55:00Z", "subject": ["Bicycles and Bicycling", "Tour de France (Bicycle Race)"], "organizations": null, "news_desk": "Sports", "lead_paragraph": "Tour de France riders arrived in Pau from Samatan, west of Toulouse, on a leisurely 158.5 kilometer stage, or 99 miles, won by Pierrick F\u00e9drigo, who rides for the FDJ-BigMat team.", "snippet": "Tour de France riders arrived in Pau from Samatan, west of Toulouse, on a leisurely 158.5 kilometer stage, or 99 miles, won by Pierrick F\u00e9drigo, who rides for the FDJ-BigMat team.", "subsection_name": "Cycling", "male": ["Pierrick"]}]