[{"anonymous": [], "word_count": "532", "_id": "547881a279881006dca8c356", "persons": ["Cashman, Brian"], "female": [], "pub_date": "2008-10-01T00:00:00Z", "subject": null, "organizations": ["New York Yankees"], "news_desk": "Sports", "lead_paragraph": "The Yankees accomplished their first goal of the off-season Tuesday when Brian Cashman accepted a three-year offer to return as general manager.", "snippet": "The Yankees accomplished their first goal of the off-season Tuesday when Brian Cashman accepted a three-year offer to return as general manager.", "subsection_name": "Baseball", "male": ["Brian"]}]