[{"anonymous": [], "word_count": "51", "_id": "5478826079881006dca8c365", "persons": ["Keith Hernandez", "Ron Darling"], "female": [], "pub_date": "2008-10-01T00:00:00Z", "subject": null, "organizations": ["Mets", "SNY"], "news_desk": "Sports", "lead_paragraph": "The TV Sports column on Tuesday, about coverage of the Mets\u2019 farewell to Shea Stadium on Sunday, misidentified the broadcaster and former player who said he had forgotten the view from the field and how the fans surrounded the players. He is Keith Hernandez, not his fellow SNY broadcaster Ron Darling.", "snippet": "The TV Sports column on Tuesday, about coverage of the Mets\u2019 farewell to Shea Stadium on Sunday, misidentified the broadcaster and former player who said he had forgotten the view from the field and how the fans surrounded the players. He is Keith...", "subsection_name": null, "male": ["Keith", "Ron"]}]