[{"anonymous": [], "word_count": "875", "_id": "548574be79881040e1d4bf78", "persons": null, "female": [], "pub_date": "2007-09-23T00:00:00Z", "subject": null, "organizations": ["N.F.L."], "news_desk": "Sports", "lead_paragraph": "If you think of the N.F.L. season as a reality show, then the first two episodes have been riveting. Last-minute plot twists. Pleasant surprises. Questions of fairness and of loyalty.", "snippet": "If you think of the N.F.L. season as a reality show, then the first two episodes have been riveting. Last-minute plot twists. Pleasant surprises. Questions of fairness and of loyalty.", "subsection_name": "Pro Football", "male": []}]