[{"anonymous": [], "word_count": "837", "_id": "547fbfc87988105a33db5cf8", "persons": null, "female": [], "pub_date": "2008-04-01T00:00:00Z", "subject": ["Stadiums and Arenas", "Yankee Stadium (NYC)", "Shea Stadium (NYC)"], "organizations": ["New York Yankees", "New York Mets"], "news_desk": "Sports", "lead_paragraph": "Brace yourself for a season of nostalgia. Everything that happens at Yankee Stadium, or Shea Stadium, for that matter, will be the last of this or the last of that.", "snippet": "Brace yourself for a season of nostalgia. Everything that happens at Yankee Stadium, or Shea Stadium, for that matter, will be the last of this or the last of that.", "subsection_name": "Baseball", "male": []}]