[{"anonymous": ["Adewale"], "word_count": "1485", "_id": "54a7a2d879881073e891410a", "persons": ["Ogunleye, Adewale"], "female": [], "pub_date": "2006-11-17T00:00:00Z", "subject": ["Football"], "organizations": ["Chicago Bears"], "news_desk": "Sports", "lead_paragraph": "For Bears defensive end Adewale Ogunleye and his family, the stories are unique, but familiar to everyone in the projects of their old neighborhood on Staten Island.\n", "snippet": "For Bears defensive end Adewale Ogunleye and his family, the stories are unique, but familiar to everyone in the projects of their old neighborhood on Staten Island.", "subsection_name": "Pro Football", "male": []}]