[{"anonymous": [], "word_count": "497", "_id": "515b995bfdc59278db00d20f", "persons": ["Karlsson, Robert", "Frazar, Harrison"], "female": [], "pub_date": "2011-06-12T00:00:00Z", "subject": ["Golf"], "organizations": ["PGA Tour Inc"], "news_desk": "Sports", "lead_paragraph": "After early dominance by Robert Karlsson, the lead at the St. Jude Classic dwindles to a single shot.", "snippet": "After early dominance by Robert Karlsson, the lead at the St. Jude Classic dwindles to a single shot.", "subsection_name": "Golf", "male": ["Robert", "Harrison"]}]