[{"anonymous": [], "word_count": "53", "_id": "540ef76d79881045f3791c2a", "persons": ["Juan Mauricio Soler"], "female": [], "pub_date": "2011-06-22T00:00:00Z", "subject": ["Sports Injuries", "Bicycles and Bicycling"], "organizations": ["Movistar"], "news_desk": "Sports", "lead_paragraph": "Juan Mauricio Soler is out of danger after sustaining severe head injuries in a crash in the Tour of Switzerland last week, his Movistar team said.", "snippet": "Juan Mauricio Soler is out of danger after sustaining severe head injuries in a crash in the Tour of Switzerland last week, his Movistar team said.", "subsection_name": "Cycling", "male": ["Juan"]}]