[{"anonymous": [], "word_count": "864", "_id": "5458c426798810533a8debfa", "persons": ["Mauer, Joe"], "female": [], "pub_date": "2009-11-23T00:00:00Z", "subject": ["Baseball", "Awards, Decorations and Honors", "Free Agents (Sports)", "Wages and Salaries", "Trades (Sports)"], "organizations": ["Minnesota Twins"], "news_desk": "Sports", "lead_paragraph": "If Joe Mauer, who established career highs in home runs and runs batted in, beats out the Yankees\u2019 Mark Teixeira and Derek Jeter for the award, industry observers will not be surprised.", "snippet": "If Joe Mauer, who established career highs in home runs and runs batted in, beats out the Yankees\u2019 Mark Teixeira and Derek Jeter for the award, industry observers will not be surprised.", "subsection_name": "Baseball", "male": ["Joe"]}]