[{"anonymous": [], "word_count": "277", "_id": "522a996779881007d59160cb", "persons": null, "female": [], "pub_date": "2013-09-07T00:00:00Z", "subject": ["Baseball"], "organizations": ["New York Yankees", "American League"], "news_desk": "Sports", "lead_paragraph": "A look at the Yankees\u2019 postseason chances using a calculation that includes a team\u2019s current win rate, the strength of their remaining schedule and their home-field advantage.", "snippet": "A look at the Yankees\u2019 postseason chances using a calculation that includes a team\u2019s current win rate, the strength of their remaining schedule and their home-field advantage.", "subsection_name": "Baseball", "male": []}]