[{"anonymous": [], "word_count": "800", "_id": "524255c1798810263f381aec", "persons": null, "female": [], "pub_date": "2013-09-25T00:00:00Z", "subject": ["Baseball"], "organizations": ["New York Yankees", "Tampa Bay Rays"], "news_desk": "Sports", "lead_paragraph": "With a shut-out loss, the Yankees were eliminated from the American League\u2019s first wild-card spot Tuesday as they fell six games behind the Rays with five to play.", "snippet": "With a shut-out loss, the Yankees were eliminated from the American League\u2019s first wild-card spot Tuesday as they fell six games behind the Rays with five to play.", "subsection_name": "Baseball", "male": []}]