[{"anonymous": [], "word_count": "131", "_id": "523a717d79881007d591a779", "persons": ["Messi, Lionel"], "female": [], "pub_date": "2013-09-19T00:00:00Z", "subject": ["Soccer"], "organizations": ["Barcelona (Soccer Team)"], "news_desk": "Sports", "lead_paragraph": "Lionel Messi scored a hat trick as Barcelona opened its Champions League campaign with a dominant 4-0 win over visiting Ajax.", "snippet": "Lionel Messi scored a hat trick as Barcelona opened its Champions League campaign with a dominant 4-0 win over visiting Ajax.", "subsection_name": null, "male": ["Lionel"]}]