[{"anonymous": ["Tiger"], "word_count": "850", "_id": "54b1ed08798810617c69a54b", "persons": ["Woods, Tiger", "Garcia, Sergio", "Furyk, Jim", "Montgomerie, Colin"], "female": [], "pub_date": "2006-09-23T00:00:00Z", "subject": ["Ryder Cup (Golf)", "Golf"], "organizations": null, "news_desk": "Sports", "lead_paragraph": "The Europeans rode the emotion of Ireland\u2019s first day as Ryder Cup host, racing out to a 5-3 lead over the United States.", "snippet": "The Europeans rode the emotion of Ireland\u2019s first day as Ryder Cup host, racing out to a 5-3 lead over the United States.", "subsection_name": "Golf", "male": ["Sergio", "Jim", "Colin"]}]