[{"anonymous": [], "word_count": "1642", "_id": "54b1c04f798810617c699fc0", "persons": null, "female": [], "pub_date": "2006-09-17T00:00:00Z", "subject": ["Interscholastic Athletics", "Television", "Football", "Education and Schools", "Athletics and Sports", "Coaches and Managers", "Advertising and Marketing"], "organizations": ["MTV Networks", "Nike Inc", "ESPN", "Fox Sports Net"], "news_desk": "Sports", "lead_paragraph": "National broadcasts of high school football have put coaches in the spotlight, and in potentially dangerous territory.", "snippet": "National broadcasts of high school football have put coaches in the spotlight, and in potentially dangerous territory.", "subsection_name": null, "male": []}]