[{"anonymous": ["Yogi", "C"], "word_count": "998", "_id": "54698cfb7988101de50ece77", "persons": ["Posada, Jorge", "Berra, Yogi", "Marte, Damaso", "Sabathia, C C", "Sizemore, Grady", "Jeter, Derek", "Damon, Johnny"], "female": [], "pub_date": "2009-04-17T00:00:00Z", "subject": ["Baseball", "Yankee Stadium (NYC)"], "organizations": ["New York Yankees", "Cleveland Indians"], "news_desk": "Sports", "lead_paragraph": "Baseball\u2019s priciest ballpark opened with a performance hardly befitting the legacy of Babe Ruth, Lou Gehrig and Mickey Mantle.", "snippet": "Baseball\u2019s priciest ballpark opened with a performance hardly befitting the legacy of Babe Ruth, Lou Gehrig and Mickey Mantle.", "subsection_name": "Baseball", "male": ["Jorge", "Damaso", "Grady", "Derek", "Johnny"]}]