[{"anonymous": [], "word_count": "403", "_id": "5469a4c57988101de50ed07d", "persons": null, "female": [], "pub_date": "2009-04-20T00:00:00Z", "subject": ["Hockey, Ice"], "organizations": ["Red Wings", "Columbus Blue Jackets"], "news_desk": "Sports", "lead_paragraph": "After a mundane regular season, the Red Wings, the defending Stanley Cup champions, have been almost perfect in their series with the Columbus Blue Jackets.", "snippet": "After a mundane regular season, the Red Wings, the defending Stanley Cup champions, have been almost perfect in their series with the Columbus Blue Jackets.", "subsection_name": "Hockey", "male": []}]