[{"anonymous": [], "word_count": "152", "_id": "515b4ed2fdc59278db007d29", "persons": ["Bowyer, Clint"], "female": [], "pub_date": "2012-06-25T00:00:00Z", "subject": ["Automobile Racing"], "organizations": null, "news_desk": "Sports", "lead_paragraph": "Clint Bowyer raced to his first victory on a road course, and first with Michael Waltrip Racing, holding off Kurt Busch in the Nascar Sprint Cup race in Sonoma, Calif.", "snippet": "Clint Bowyer raced to his first victory on a road course, and first with Michael Waltrip Racing, holding off Kurt Busch in the Nascar Sprint Cup race in Sonoma, Calif.", "subsection_name": "Auto Racing", "male": ["Clint"]}]