[{"anonymous": [], "word_count": "33", "_id": "524972d87988105ad44f4be0", "persons": ["Lily"], "female": ["Lily"], "pub_date": "2011-01-16T20:19:22Z", "subject": ["Dogs"], "organizations": null, "news_desk": "Sports", "lead_paragraph": "While hip replacement surgery for larger dogs has been around since the mid-1970s, hip replacement surgery for smaller dogs like Lily who weigh between 6 and 30 lbs, only became available in 2006. ", "snippet": "While hip replacement surgery for larger dogs has been around since the mid-1970s, hip replacement surgery for smaller dogs like Lily who weigh between 6 and 30 lbs, only became available in 2006.", "subsection_name": null, "male": []}]