[{"anonymous": [], "word_count": "170", "_id": "5424ccd479881017ba4e8baa", "persons": ["Danny Mwanga"], "female": [], "pub_date": "2010-01-15T00:00:00Z", "subject": ["Soccer"], "organizations": ["Major League Soccer"], "news_desk": "Sports", "lead_paragraph": "The Philadelphia Union selected Oregon State forward Danny Mwanga with the first overall selection in the Major League Soccer draft on Thursday in Philadelphia.", "snippet": "The Philadelphia Union selected Oregon State forward Danny Mwanga with the first overall selection in the Major League Soccer draft on Thursday in Philadelphia.", "subsection_name": "Soccer", "male": ["Danny"]}]