[{"anonymous": [], "word_count": "789", "_id": "53c9387f7988102406602bf9", "persons": ["Clarke, Darren", "Mickelson, Phil", "Coetzee, George", "Hamilton, Todd"], "female": [], "pub_date": "2014-07-19T00:00:00Z", "subject": ["Golf", "British Open (Golf)"], "organizations": null, "news_desk": "Sports", "lead_paragraph": "Phil Mickelson had his first below-par score in a major since winning last year&#8217;s British Open, but he is 12 shots behind the leader, Rory McIlroy.", "snippet": "Phil Mickelson had his first below-par score in a major since winning last year&#8217;s British Open, but he is 12 shots behind the leader, Rory McIlroy.", "subsection_name": "Golf", "male": ["Darren", "Phil", "George", "Todd"]}]