[{"anonymous": [], "word_count": "425", "_id": "52f8491c7988104fb72f46be", "persons": ["Smart, Marcus"], "female": [], "pub_date": "2014-02-10T00:00:00Z", "subject": ["Basketball (College)"], "organizations": ["Oklahoma State University", "University of North Carolina", "Duke University", "University of Texas at Austin"], "news_desk": "Sports", "lead_paragraph": "After losing star guard Marcus Smart to suspension, No. 19 Oklahoma State faces a daunting pair of games this week, traveling to No. 15 Texas before hosting No. 21 Oklahoma.", "snippet": "After losing star guard Marcus Smart to suspension, No. 19 Oklahoma State faces a daunting pair of games this week, traveling to No. 15 Texas before hosting No. 21 Oklahoma.", "subsection_name": "College Basketball", "male": ["Marcus"]}]