[{"anonymous": ["A.J."], "word_count": "513", "_id": "5418a55a7988106440c98d8e", "persons": ["Burnett, A.J."], "female": [], "pub_date": "2010-07-18T00:00:00Z", "subject": ["Baseball"], "organizations": ["New York Yankees", "Tampa Bay Rays"], "news_desk": "Sports", "lead_paragraph": "A. J. Burnett pitched poorly, then had to leave in the third inning after cutting his hands when he struck the clubhouse doors out of frustration.", "snippet": "A. J. Burnett pitched poorly, then had to leave in the third inning after cutting his hands when he struck the clubhouse doors out of frustration.", "subsection_name": "Baseball", "male": []}]