[{"anonymous": [], "word_count": "557", "_id": "54b0f42a7988100e21966746", "persons": ["Greg Bisconti"], "female": [], "pub_date": "2006-08-18T00:00:00Z", "subject": ["PGA Championship", "Golf"], "organizations": ["Medinah"], "news_desk": "Sports", "lead_paragraph": "Greg Bisconti is one of 20 club professionals who qualified for the P.G.A. Championship, and Medinah represents his first appearance in a major.", "snippet": "Greg Bisconti is one of 20 club professionals who qualified for the P.G.A. Championship, and Medinah represents his first appearance in a major.", "subsection_name": "Golf", "male": ["Greg"]}]