[{"anonymous": [], "word_count": "877", "_id": "549b586f7988100306690fea", "persons": ["Hingis, Martina"], "female": ["Martina"], "pub_date": "2006-08-31T00:00:00Z", "subject": ["United States Open (Tennis)", "Tennis"], "organizations": null, "news_desk": "Sports", "lead_paragraph": "After a long sabbatical, nursing a foot injury and pondering her future, Martina Hingis has come back to take on the big hitters of the women\u2019s tour.", "snippet": "After a long sabbatical, nursing a foot injury and pondering her future, Martina Hingis has come back to take on the big hitters of the women\u2019s tour.", "subsection_name": "Tennis", "male": []}]