[{"anonymous": ["Pont"], "word_count": "573", "_id": "5482bee77988101355141042", "persons": ["Pont"], "female": [], "pub_date": "2008-07-03T00:00:00Z", "subject": ["Football", "Deaths (Obituaries)"], "organizations": ["Indiana University"], "news_desk": "Sports", "lead_paragraph": "Mr. Pont was a football-coaching lifer who was best remembered for taking Indiana University to its first bowl game in 1968.", "snippet": "Mr. Pont was a football-coaching lifer who was best remembered for taking Indiana University to its first bowl game in 1968.", "subsection_name": "College Football", "male": []}]