[{"anonymous": [], "word_count": "882", "_id": "515aa58ffdc59278db006214", "persons": ["Chris Higgins", "Maxim Lapierre"], "female": [], "pub_date": "2011-05-26T00:00:00Z", "subject": ["Hockey, Ice", "Playoff Games", "Trades (Sports)"], "organizations": ["Vancouver Canucks"], "news_desk": "Sports", "lead_paragraph": "Chris Higgins and Maxim Lapierre, both acquired at the trade deadline, have played well this postseason.", "snippet": "Chris Higgins and Maxim Lapierre, both acquired at the trade deadline, have played well this postseason.", "subsection_name": "Hockey", "male": ["Chris", "Maxim"]}]